egenix/__init__.py
egenix-1.0.0.dist-info/LICENSE
egenix-1.0.0.dist-info/METADATA
egenix-1.0.0.dist-info/WHEEL
egenix-1.0.0.dist-info/top_level.txt
egenix-1.0.0.dist-info/RECORD
